src/ThisIsAServerSample.py
src/__init__.py
src/cache.py
src/citzer.py
src/click50.py
src/client.py
src/cssci.py
src/extractlink.py
src/ifverify.py
src/main.py
src/searcher.py
src/server.py
src/worker.py
cnks-0.3.2.dist-info/METADATA
cnks-0.3.2.dist-info/WHEEL
cnks-0.3.2.dist-info/entry_points.txt
cnks-0.3.2.dist-info/RECORD
