Metadata-Version: 2.4
Name: cnks
Version: 0.3.2
Summary: 中国知网搜索与引文处理系统
Author-email: bai-z-l <b@iziliang.com>
Requires-Python: >=3.12
Requires-Dist: mcp[cli]>=1.6.0
Requires-Dist: playwright>=1.40.0
Requires-Dist: python-dotenv>=1.0.0
